aiows/__init__.py
aiows/config.py
aiows/dispatcher.py
aiows/exceptions.py
aiows/factory.py
aiows/filters.py
aiows/health.py
aiows/router.py
aiows/server.py
aiows/settings.py
aiows/validators.py
aiows/websocket.py
aiows/middleware/__init__.py
aiows/middleware/auth.py
aiows/middleware/base.py
aiows/middleware/connection_limiter.py
aiows/middleware/logging.py
aiows/middleware/rate_limit.py
aiows/types/__init__.py
aiows-0.1.2.dist-info/licenses/LICENSE
aiows-0.1.2.dist-info/METADATA
aiows-0.1.2.dist-info/WHEEL
aiows-0.1.2.dist-info/top_level.txt
aiows-0.1.2.dist-info/RECORD
